netbox_vault/__init__.py
netbox_vault/navigation.py
netbox_vault/tables.py
netbox_vault/urls.py
netbox_vault/api/__init__.py
netbox_vault/api/serializers.py
netbox_vault/api/urls.py
netbox_vault/api/views.py
netbox_vault/forms/__init__.py
netbox_vault/forms/forms.py
netbox_vault/migrations/0001_initial.py
netbox_vault/migrations/__init__.py
netbox_vault/models/__init__.py
netbox_vault/models/vault.py
netbox_vault/templates/vault/vault.html
netbox_vault/views/__init__.py
netbox_vault/views/vault.py
netbox_vault-0.1.8.dist-info/METADATA
netbox_vault-0.1.8.dist-info/WHEEL
netbox_vault-0.1.8.dist-info/top_level.txt
netbox_vault-0.1.8.dist-info/RECORD
