Metadata-Version: 2.1
Name: netbox-vault
Version: 0.1.8
Summary: Connexion to Vault - DW - Netbox
Author-email: Arthur ASCEDU <aascedu@student.42lyon.fr>
Classifier: Development Status :: 3 - Alpha
Classifier: Intended Audience :: Developers
Classifier: Natural Language :: English
Classifier: Programming Language :: Python :: 3 :: Only
Classifier: Programming Language :: Python :: 3.10
Classifier: Programming Language :: Python :: 3.11
Classifier: Programming Language :: Python :: 3.12
Requires-Python: >=3.10.0
